setup.cfg
setup.py
fuzzyattr/__init__.py
fuzzyattr/fuzzyattr.py
fuzzyattr.egg-info/PKG-INFO
fuzzyattr.egg-info/SOURCES.txt
fuzzyattr.egg-info/dependency_links.txt
fuzzyattr.egg-info/requires.txt
fuzzyattr.egg-info/top_level.txt