Metadata-Version: 1.1
Name: fuzzyattr
Version: 0.1.1
Summary: fuzzyattr matches the closest attribute name in python so you can make unlimited free typos.
Home-page: https://github.com/urill/fuzzyattr
Author: Keshuai Xu
Author-email: urillx@gmail.com
License: UNKNOWN
Keywords: fuzzy match attribute function method
Platform: UNKNOWN
Classifier: Development Status :: 4 - Beta
Classifier: Intended Audience :: Developers
Classifier: Topic :: Software Development
Classifier: License :: OSI Approved :: MIT License
Classifier: Programming Language :: Python :: 3
Classifier: Programming Language :: Python :: 3.4
Classifier: Programming Language :: Python :: 3.5
Classifier: Programming Language :: Python :: 3.6
